postgrest/__init__.py
postgrest/_async/__init__.py
postgrest/_async/client.py
postgrest/_async/request_builder.py
postgrest/_sync/__init__.py
postgrest/_sync/client.py
postgrest/_sync/request_builder.py
postgrest/base_client.py
postgrest/base_request_builder.py
postgrest/constants.py
postgrest/exceptions.py
postgrest/py.typed
postgrest/types.py
postgrest/utils.py
postgrest/version.py
postgrest-2.23.1.dist-info/WHEEL
postgrest-2.23.1.dist-info/METADATA
postgrest-2.23.1.dist-info/RECORD
