Metadata-Version: 2.4
Name: postgrest
Version: 2.23.1
Summary: PostgREST client for Python. This library provides an ORM interface to PostgREST.
Author: Lương Quang Mạnh, Joel Lee, Anand, Oliver Rice, Andrew Smith
Author-email: Lương Quang Mạnh <luongquangmanh85@gmail.com>, Joel Lee <joel@joellee.org>, Andrew Smith <a.smith@silentworks.co.uk>
License-Expression: MIT
Classifier: Programming Language :: Python :: 3
Classifier: License :: OSI Approved :: MIT License
Classifier: Operating System :: OS Independent
Requires-Dist: httpx[http2]>=0.26,<0.29
Requires-Dist: deprecation>=2.1.0
Requires-Dist: pydantic>=1.9,<3.0
Requires-Dist: strenum>=0.4.9 ; python_full_version < '3.11'
Requires-Dist: yarl>=1.20.1
Maintainer: Leonardo Santiago
Maintainer-email: Leonardo Santiago <leonardo.santiago@supabase.io>
Requires-Python: >=3.9
Project-URL: changelog, https://github.com/supabase/supabase-py/tree/main/CHANGELOG.md
Project-URL: documentation, https://postgrest-py.rtfd.io
Project-URL: homepage, https://github.com/supabase/supabase/tree/main/src/postgrest
Project-URL: repository, https://github.com/supabase/supabase-py
